LICENSE
setup.py
django_trackmodels_ritual.egg-info/PKG-INFO
django_trackmodels_ritual.egg-info/SOURCES.txt
django_trackmodels_ritual.egg-info/dependency_links.txt
django_trackmodels_ritual.egg-info/requires.txt
django_trackmodels_ritual.egg-info/top_level.txt
grimoire/django/tracked/__init__.py
grimoire/django/tracked/admin.py
grimoire/django/tracked/reports.py
grimoire/django/tracked/locale/en/LC_MESSAGES/django.mo
grimoire/django/tracked/locale/en/LC_MESSAGES/django.po
grimoire/django/tracked/locale/es/LC_MESSAGES/django.mo
grimoire/django/tracked/locale/es/LC_MESSAGES/django.po
grimoire/django/tracked/models/__init__.py
grimoire/django/tracked/models/common.py
grimoire/django/tracked/models/polymorphic.py
grimoire/django/tracked/templates/admin/tracking_report_error.html
grimoire/django/tracked/templates/admin/tracked/change_list.html